doreah/__init__.py
doreah/_color.py
doreah/auth.py
doreah/configuration.py
doreah/control.py
doreah/io.py
doreah/keystore.py
doreah/logging.py
doreah/persistence.py
doreah/regular.py
doreah/resources/auth/login.html.jinja
doreah/resources/configuration/settings.jinja
doreah/resources/configuration/settings.md.jinja
doreah/resources/configuration/types/Boolean.jinja
doreah/resources/configuration/types/Choice.jinja
doreah/resources/configuration/types/Integer.jinja
doreah/resources/configuration/types/List.jinja
doreah/resources/configuration/types/MultiChoice.jinja
doreah/resources/configuration/types/Set.jinja
doreah/resources/configuration/types/String.jinja
doreah/resources/keystore/settings.jinja
doreah-2.0.1.dist-info/entry_points.txt
doreah-2.0.1.dist-info/LICENSE
doreah-2.0.1.dist-info/WHEEL
doreah-2.0.1.dist-info/METADATA
doreah-2.0.1.dist-info/RECORD
