Metadata-Version: 2.1
Name: doreah
Version: 2.0.1
Summary: Small toolkit of utilities for python projects
Keywords: library,tools
Author-email: Johannes Krattenmacher <doreah@dev.krateng.ch>
Requires-Python: >=3.11
Classifier: Programming Language :: Python :: 3
Classifier: License :: OSI Approved :: GNU General Public License v3 (GPLv3)
Classifier: Operating System :: OS Independent
Requires-Dist: requests
Requires-Dist: pyyaml
Requires-Dist: jinja2>2.11
Requires-Dist: bcrypt
Project-URL: documentation, https://doreah.readthedocs.io/en/latest/
Project-URL: repository, https://github.com/krateng/doreah
